Metadata-Version: 1.0
Name: bqLie
Version: 1.1.0
Summary: 上传测试包
Home-page: UNKNOWN
Author: UNKNOWN
Author-email: UNKNOWN
License: MIT
Platform: UNKNOWN
